xlsext/__init__.py
xlsext/extensions.py
xlsext-1.0.1.dist-info/METADATA
xlsext-1.0.1.dist-info/WHEEL
xlsext-1.0.1.dist-info/top_level.txt
xlsext-1.0.1.dist-info/RECORD
